extract_openreview_comments/__init__.py
extract_openreview_comments/cli.py
extract_openreview_comments/client.py
extract_openreview_comments/formatter.py
extract_openreview_comments-0.1.1.dist-info/METADATA
extract_openreview_comments-0.1.1.dist-info/WHEEL
extract_openreview_comments-0.1.1.dist-info/entry_points.txt
extract_openreview_comments-0.1.1.dist-info/licenses/LICENSE
extract_openreview_comments-0.1.1.dist-info/RECORD
