Metadata-Version: 2.4
Name: extract-openreview-comments
Version: 0.1.1
Summary: A python script to extract the open-review comments for a paper into a markdown file for easy copy/pasting during rebuttals
Project-URL: Homepage, https://github.com/chanind/extract-openreview-comments
Project-URL: Repository, https://github.com/chanind/extract-openreview-comments
Project-URL: Issues, https://github.com/chanind/extract-openreview-comments/issues
Author-email: David Chanin <chanindav@gmail.com>
License: MIT
License-File: LICENSE
Keywords: comments,markdown,openreview,rebuttal
Classifier: Development Status :: 3 - Alpha
Classifier: Intended Audience :: Science/Research
Classifier: License :: OSI Approved :: MIT License
Classifier: Programming Language :: Python :: 3
Classifier: Programming Language :: Python :: 3.11
Classifier: Programming Language :: Python :: 3.12
Requires-Python: >=3.11
Requires-Dist: click>=8.0.0
Requires-Dist: openreview-py>=1.0.0
